MANIFEST.in
README.md
pyproject.toml
setup.cfg
setup.py
baseapp_social_auth/__init__.py
baseapp_social_auth/referrals.py
baseapp_social_auth/serializers.py
baseapp_social_auth/settings.py
baseapp_social_auth/views.py
baseapp_social_auth.egg-info/PKG-INFO
baseapp_social_auth.egg-info/SOURCES.txt
baseapp_social_auth.egg-info/dependency_links.txt
baseapp_social_auth.egg-info/requires.txt
baseapp_social_auth.egg-info/top_level.txt
baseapp_social_auth/cache/__init__.py
baseapp_social_auth/cache/admin.py
baseapp_social_auth/cache/models.py
baseapp_social_auth/cache/pipeline.py
baseapp_social_auth/cache/tasks.py
baseapp_social_auth/cache/migrations/0001_initial.py
baseapp_social_auth/cache/migrations/0002_alter_socialauthaccesstokencache_id.py
baseapp_social_auth/cache/migrations/0003_alter_socialauthaccesstokencache_id.py
baseapp_social_auth/cache/migrations/0004_alter_socialauthaccesstokencache_id.py
baseapp_social_auth/cache/migrations/__init__.py
baseapp_social_auth/tests/__init__.py
baseapp_social_auth/tests/conftest.py
baseapp_social_auth/tests/pipeline.py
baseapp_social_auth/tests/intergration/__init__.py
baseapp_social_auth/tests/intergration/test_migration_health_check.py
baseapp_social_auth/tests/intergration/test_views.py
baseapp_social_auth/tests/unit/__init__.py
baseapp_social_auth/tests/unit/test_tasks.py
testproject/__init__.py
testproject/settings.py
testproject/urls.py
testproject/wsgi.py
testproject/testapp/__init__.py
testproject/testapp/admin.py
testproject/testapp/models.py
testproject/testapp/migrations/0001_initial.py
testproject/testapp/migrations/0002_alter_user_id.py
testproject/testapp/migrations/__init__.py